zarnitsa/DataAugmenter.py
zarnitsa/__init__.py
zarnitsa/nlp/DataAugmenterNLP.py
zarnitsa/nlp/__init__.py
zarnitsa/series/DataAugmenterTimeSeries.py
zarnitsa/series/__init__.py
zarnitsa/stats/DataAugmenterExternally.py
zarnitsa/stats/DataAugmenterInternally.py
zarnitsa/stats/__init__.py
zarnitsa-0.0.19.dist-info/LICENSE
zarnitsa-0.0.19.dist-info/METADATA
zarnitsa-0.0.19.dist-info/WHEEL
zarnitsa-0.0.19.dist-info/top_level.txt
zarnitsa-0.0.19.dist-info/RECORD
