Metadata-Version: 2.1
Name: zarnitsa
Version: 0.0.19
Summary: zarnitsa package for data augmentation
Home-page: https://github.com/AlexKay28/zarnitsa
Author: Kaigorodov Alexander
Author-email: kaygorodo2305@gmail.com
License: UNKNOWN
Download-URL: https://pypi.org/project/zarnitsa/
Keywords: augmentation,NLP,distributions
Platform: UNKNOWN
License-File: LICENSE
Requires-Dist: numpy (>=1.16.1)
Requires-Dist: pandas (>=1.1.5)
Requires-Dist: scikit-learn (>=0.23.2)
Requires-Dist: nlpaug (==1.1.3)
Requires-Dist: wget (>=3.2)
Requires-Dist: spacy (>=3.0.5)
